YunJisuanjishuYuYingyongXuexiJiaochengCYuyanBianchengWang/README.md
YunJisuanjishuYuYingyongXuexiJiaochengCYuyanBianchengWang/__init__.py
YunJisuanjishuYuYingyongXuexiJiaochengCYuyanBianchengWang/__main__.py
YunJisuanjishuYuYingyongXuexiJiaochengCYuyanBianchengWang/file.epub
YunJisuanjishuYuYingyongXuexiJiaochengCYuyanBianchengWang/index.html
YunJisuanjishuYuYingyongXuexiJiaochengCYuyanBianchengWang/css/__init__.py
YunJisuanjishuYuYingyongXuexiJiaochengCYuyanBianchengWang/css/annotations.css
YunJisuanjishuYuYingyongXuexiJiaochengCYuyanBianchengWang/css/main.css
YunJisuanjishuYuYingyongXuexiJiaochengCYuyanBianchengWang/css/normalize.css
YunJisuanjishuYuYingyongXuexiJiaochengCYuyanBianchengWang/css/popup.css
YunJisuanjishuYuYingyongXuexiJiaochengCYuyanBianchengWang/font/__init__.py
YunJisuanjishuYuYingyongXuexiJiaochengCYuyanBianchengWang/font/fontello.eot
YunJisuanjishuYuYingyongXuexiJiaochengCYuyanBianchengWang/font/fontello.svg
YunJisuanjishuYuYingyongXuexiJiaochengCYuyanBianchengWang/font/fontello.ttf
YunJisuanjishuYuYingyongXuexiJiaochengCYuyanBianchengWang/font/fontello.woff
YunJisuanjishuYuYingyongXuexiJiaochengCYuyanBianchengWang/img/__init__.py
YunJisuanjishuYuYingyongXuexiJiaochengCYuyanBianchengWang/img/annotator-glyph-sprite.png
YunJisuanjishuYuYingyongXuexiJiaochengCYuyanBianchengWang/img/annotator-icon-sprite.png
YunJisuanjishuYuYingyongXuexiJiaochengCYuyanBianchengWang/img/apple-touch-icon.png
YunJisuanjishuYuYingyongXuexiJiaochengCYuyanBianchengWang/img/cancelfullscreen.png
YunJisuanjishuYuYingyongXuexiJiaochengCYuyanBianchengWang/img/close.png
YunJisuanjishuYuYingyongXuexiJiaochengCYuyanBianchengWang/img/fullscreen.png
YunJisuanjishuYuYingyongXuexiJiaochengCYuyanBianchengWang/img/loader.gif
YunJisuanjishuYuYingyongXuexiJiaochengCYuyanBianchengWang/img/menu-icon.png
YunJisuanjishuYuYingyongXuexiJiaochengCYuyanBianchengWang/img/save.png
YunJisuanjishuYuYingyongXuexiJiaochengCYuyanBianchengWang/img/saved.png
yun_jisuanjishu_yu_yingyong_xuexi_jiaocheng_c_yuyan_biancheng_wang-2024.3.5.0.dist-info/METADATA
yun_jisuanjishu_yu_yingyong_xuexi_jiaocheng_c_yuyan_biancheng_wang-2024.3.5.0.dist-info/WHEEL
yun_jisuanjishu_yu_yingyong_xuexi_jiaocheng_c_yuyan_biancheng_wang-2024.3.5.0.dist-info/entry_points.txt
yun_jisuanjishu_yu_yingyong_xuexi_jiaocheng_c_yuyan_biancheng_wang-2024.3.5.0.dist-info/top_level.txt
yun_jisuanjishu_yu_yingyong_xuexi_jiaocheng_c_yuyan_biancheng_wang-2024.3.5.0.dist-info/RECORD
